codeup/__init__.py
codeup/aicommit.py
codeup/api.py
codeup/args.py
codeup/cli.py
codeup/command_runner.py
codeup/config.py
codeup/console.py
codeup/git_utils.py
codeup/keyring.py
codeup/main.py
codeup/shebang_processor.py
codeup/timestamp_formatter.py
codeup/utils.py
codeup/assets/example.txt
codeup-1.0.24.dist-info/licenses/LICENSE
codeup-1.0.24.dist-info/METADATA
codeup-1.0.24.dist-info/WHEEL
codeup-1.0.24.dist-info/entry_points.txt
codeup-1.0.24.dist-info/top_level.txt
codeup-1.0.24.dist-info/RECORD
