Metadata-Version: 2.4
Name: codeup
Version: 1.0.24
Summary: Intelligent git workflow automation tool with AI-powered commit messages
Home-page: https://github.com/zackees/codeup
Author-email: Zach Vorhies <zach@zachvorhies.com>
Maintainer: Zachary Vorhies
License: MIT
Project-URL: Homepage, https://github.com/zackees/codeup
Project-URL: Repository, https://github.com/zackees/codeup
Project-URL: Issues, https://github.com/zackees/codeup/issues
Project-URL: Documentation, https://github.com/zackees/codeup#readme
Keywords: git,ai,commit,automation,workflow
Classifier: Development Status :: 5 - Production/Stable
Classifier: Intended Audience :: Developers
Classifier: License :: OSI Approved :: MIT License
Classifier: Operating System :: OS Independent
Classifier: Programming Language :: Python :: 3
Classifier: Programming Language :: Python :: 3.10
Classifier: Programming Language :: Python :: 3.11
Classifier: Programming Language :: Python :: 3.12
Classifier: Programming Language :: Python :: 3.13
Classifier: Topic :: Software Development :: Version Control :: Git
Classifier: Topic :: Software Development :: Libraries :: Python Modules
Requires-Python: >=3.10
License-File: LICENSE
Requires-Dist: openai>=1.0.0
Requires-Dist: anthropic>=0.18.0
Requires-Dist: appdirs>=1.4.4
Requires-Dist: keyring>=24.0.0
Requires-Dist: semi_secret>=1.0.0
Requires-Dist: running-process>=1.0.6
Requires-Dist: colorama>=0.4.6
Provides-Extra: dev
Requires-Dist: pytest>=7.0.0; extra == "dev"
Requires-Dist: pytest-cov>=4.0.0; extra == "dev"
Requires-Dist: pytest-xdist>=3.0.0; extra == "dev"
Requires-Dist: pytest-timeout>=2.0.0; extra == "dev"
Requires-Dist: black>=23.0.0; extra == "dev"
Requires-Dist: isort>=5.12.0; extra == "dev"
Requires-Dist: ruff>=0.1.0; extra == "dev"
Requires-Dist: pyright>=1.1.0; extra == "dev"
Dynamic: home-page
Dynamic: license-file
Dynamic: maintainer
